README.rst
setup.py
shaderdef/__init__.py
shaderdef/ast_util.py
shaderdef/attr_rename.py
shaderdef/find_function.py
shaderdef/glsl_funcs.py
shaderdef/glsl_types.py
shaderdef/glsl_var.py
shaderdef/interface.py
shaderdef/lift_attributes.py
shaderdef/py_to_glsl.py
shaderdef/rename_ast_nodes.py
shaderdef/rewrite_output.py
shaderdef/shader.py
shaderdef/stage.py
shaderdef/version.py
shaderdef.egg-info/PKG-INFO
shaderdef.egg-info/SOURCES.txt
shaderdef.egg-info/dependency_links.txt
shaderdef.egg-info/requires.txt
shaderdef.egg-info/top_level.txt
shaderdef.egg-info/zip-safe
test/test_ast.py
test/test_code_gen.py
test/test_demo.py
test/test_docstrings.py
test/test_glsl_types.py
test/test_glsl_var.py
test/test_interface.py
test/test_renames.py
test/test_shader.py
test/test_stage.py
tools/__init__.py
tools/release.py
tools/version_util.py