Metadata-Version: 1.0
Name: shaderdef
Version: 0.8.3
Summary: Transform Python code into GLSL shaders
Home-page: https://github.com/nicholasbishop/shaderdef
Author: Nicholas Bishop
Author-email: nicholasbishop@gmail.com
License: GNU General Public License v3 or later (GPLv3+)
Platform: UNKNOWN
